hexway_hive_api/__init__.py
hexway_hive_api/clients/__init__.py
hexway_hive_api/clients/async_rest_client.py
hexway_hive_api/clients/rest_client.py
hexway_hive_api/rest/__init__.py
hexway_hive_api/rest/enums.py
hexway_hive_api/rest/error_handler.py
hexway_hive_api/rest/exceptions.py
hexway_hive_api/rest/http_client/__init__.py
hexway_hive_api/rest/http_client/async_http_client.py
hexway_hive_api/rest/http_client/exceptions.py
hexway_hive_api/rest/http_client/http_client.py
hexway_hive_api/rest/models/__init__.py
hexway_hive_api/rest/models/issue.py
hexway_hive_api/rest/models/project.py
hexway_hive_api-0.2.14.dist-info/licenses/LICENSE
hexway_hive_api-0.2.14.dist-info/METADATA
hexway_hive_api-0.2.14.dist-info/WHEEL
hexway_hive_api-0.2.14.dist-info/top_level.txt
hexway_hive_api-0.2.14.dist-info/RECORD
