Metadata-Version: 2.4
Name: hexway-hive-api
Version: 0.2.14
Summary: Small wrapper for HexWay Hive API
Author-email: "@Cur1iosity" <Cur1iosity@protonmail.com>
Project-URL: Homepage, https://github.com/Cur1iosity/hexway-hive-api
Classifier: Programming Language :: Python :: 3
Classifier: License :: OSI Approved :: MIT License
Classifier: Operating System :: OS Independent
Requires-Python: >=3.12
License-File: LICENSE
Requires-Dist: requests>=2.31.0
Requires-Dist: pydantic>=2.4.0
Requires-Dist: aiohttp>=3.9.0
Provides-Extra: dev
Requires-Dist: pytest; extra == "dev"
Dynamic: license-file
